allelicimbalance/__init__.py
allelicimbalance/allelicimbalance.py
allelicimbalance-0.1.1.dist-info/LICENSE
allelicimbalance-0.1.1.dist-info/METADATA
allelicimbalance-0.1.1.dist-info/WHEEL
allelicimbalance-0.1.1.dist-info/top_level.txt
allelicimbalance-0.1.1.dist-info/RECORD
