Metadata-Version: 2.1
Name: allelicimbalance
Version: 0.1.1
Summary: Utilities for studying allelic imbalance
Home-page: https://gitlab.com/aaylward/allelicimbalance
Author: Anthony Aylward
Author-email: aaylward@salk.edu
License: UNKNOWN
Platform: UNKNOWN
Classifier: Programming Language :: Python :: 3
Classifier: License :: OSI Approved :: MIT License
Classifier: Operating System :: OS Independent
License-File: LICENSE
Requires-Dist: betabernsum
Requires-Dist: scipy
